harmonized_landsat_sentinel/CLI.py
harmonized_landsat_sentinel/HLS2_connection.py
harmonized_landsat_sentinel/HLS2_granule.py
harmonized_landsat_sentinel/HLS2_landsat_granule.py
harmonized_landsat_sentinel/HLS2_sentinel_granule.py
harmonized_landsat_sentinel/HLS_CMR_query.py
harmonized_landsat_sentinel/HLS_granule_ID.py
harmonized_landsat_sentinel/__init__.py
harmonized_landsat_sentinel/constants.py
harmonized_landsat_sentinel/daterange.py
harmonized_landsat_sentinel/earliest_datetime.py
harmonized_landsat_sentinel/exceptions.py
harmonized_landsat_sentinel/generate_HLS_timeseries.py
harmonized_landsat_sentinel/get_CMR_granule_ID.py
harmonized_landsat_sentinel/harmonized_landsat_sentinel.py
harmonized_landsat_sentinel/latest_datetime.py
harmonized_landsat_sentinel/login.py
harmonized_landsat_sentinel/parse_arguments.py
harmonized_landsat_sentinel/timer.py
harmonized_landsat_sentinel/version.py
harmonized_landsat_sentinel-2.1.0.dist-info/licenses/LICENSE
tests/test_HLS_imports.py
tests/test_import_dependencies.py
harmonized_landsat_sentinel-2.1.0.dist-info/METADATA
harmonized_landsat_sentinel-2.1.0.dist-info/WHEEL
harmonized_landsat_sentinel-2.1.0.dist-info/entry_points.txt
harmonized_landsat_sentinel-2.1.0.dist-info/top_level.txt
harmonized_landsat_sentinel-2.1.0.dist-info/RECORD
