Metadata-Version: 2.4
Name: harmonized-landsat-sentinel
Version: 2.1.0
Summary: Harmonized Landsat Sentinel (HLS) search and download utility
Author-email: "Gregory H. Halverson" <gregory.h.halverson@jpl.nasa.gov>
Project-URL: Homepage, https://github.com/STARS-Data-Fusion/harmonized-landsat-sentinel
Classifier: Programming Language :: Python :: 3
Classifier: Operating System :: OS Independent
Requires-Python: >=3.10
License-File: LICENSE
Requires-Dist: beautifulsoup4
Requires-Dist: colored-logging
Requires-Dist: earthaccess
Requires-Dist: matplotlib
Requires-Dist: numpy
Requires-Dist: pandas
Requires-Dist: pytest
Requires-Dist: python-dateutil
Requires-Dist: rasterio
Requires-Dist: rasters
Requires-Dist: requests
Requires-Dist: sentinel-tiles
Requires-Dist: shapely
Provides-Extra: dev
Requires-Dist: build; extra == "dev"
Requires-Dist: pytest>=6.0; extra == "dev"
Requires-Dist: pytest-cov; extra == "dev"
Requires-Dist: jupyter; extra == "dev"
Requires-Dist: pytest; extra == "dev"
Requires-Dist: twine; extra == "dev"
Dynamic: license-file
